CelebiChrono/__init__.py
CelebiChrono/main.py
CelebiChrono/interface/ChernManager.py
CelebiChrono/interface/ChernShell.py
CelebiChrono/interface/__init__.py
CelebiChrono/interface/chern_shell_base.py
CelebiChrono/interface/chern_shell_commands.py
CelebiChrono/interface/chern_shell_completions.py
CelebiChrono/interface/chern_shell_visualization.py
CelebiChrono/interface/commands_advanced.py
CelebiChrono/interface/commands_basic.py
CelebiChrono/interface/commands_documentation.py
CelebiChrono/interface/commands_environment.py
CelebiChrono/interface/commands_file.py
CelebiChrono/interface/commands_navigation.py
CelebiChrono/interface/commands_task.py
CelebiChrono/interface/shell.py
CelebiChrono/kernel/__init__.py
CelebiChrono/kernel/chern_cache.py
CelebiChrono/kernel/chern_communicator.py
CelebiChrono/kernel/helpme.py
CelebiChrono/kernel/valgorithm.py
CelebiChrono/kernel/vdirectory.py
CelebiChrono/kernel/vimpression.py
CelebiChrono/kernel/vobj_alias_management.py
CelebiChrono/kernel/vobj_arc_management.py
CelebiChrono/kernel/vobj_core.py
CelebiChrono/kernel/vobj_execution.py
CelebiChrono/kernel/vobj_file.py
CelebiChrono/kernel/vobj_impression.py
CelebiChrono/kernel/vobject.py
CelebiChrono/kernel/vproject.py
CelebiChrono/kernel/vtask.py
CelebiChrono/kernel/vtask_core.py
CelebiChrono/kernel/vtask_file.py
CelebiChrono/kernel/vtask_input.py
CelebiChrono/kernel/vtask_job.py
CelebiChrono/kernel/vtask_setting.py
CelebiChrono/utils/__init__.py
CelebiChrono/utils/csys.py
CelebiChrono/utils/message.py
CelebiChrono/utils/metadata.py
CelebiChrono/utils/pretty.py
UnitTest/prepare.py
UnitTest/test_cherncommunicator.py
UnitTest/test_utils.py
UnitTest/test_valgorithm.py
UnitTest/test_vobject.py
UnitTest/test_vtask.py
bin/run_standalone.py
doc/source/conf.py
celebichrono-0.0.1.dist-info/METADATA
celebichrono-0.0.1.dist-info/WHEEL
celebichrono-0.0.1.dist-info/entry_points.txt
celebichrono-0.0.1.dist-info/top_level.txt
celebichrono-0.0.1.dist-info/RECORD
