Metadata-Version: 2.4
Name: CelebiChrono
Version: 0.0.1
Summary: A data analysis management toolkit for high energy physics
Author-email: Mingrui Zhao <mingrui.zhao@mail.labz0.org>
License: Apache License, Version 2.0
Project-URL: Homepage, https://github.com/CelebiProjects/Celebi
Keywords: analysis,preservation,high-energy physics,data analysis
Classifier: Development Status :: 4 - Beta
Classifier: Intended Audience :: Science/Research
Classifier: Topic :: Scientific/Engineering :: Physics
Classifier: License :: OSI Approved :: Apache Software License
Classifier: Programming Language :: Python :: 3
Classifier: Programming Language :: Python :: Implementation :: CPython
Requires-Dist: click
Requires-Dist: colored
Requires-Dist: diff-match-patch
Requires-Dist: python-daemon
Requires-Dist: ipython
Requires-Dist: PyYAML>=5.1
Requires-Dist: requests
Requires-Dist: networkx
Requires-Dist: graphviz
Requires-Dist: plotly
